phoenix/__init__.py
phoenix/avatica.py
phoenix/client.py
phoenix/errors.py
phoenix_py-1.0.4.dev1.dist-info/DESCRIPTION.rst
phoenix_py-1.0.4.dev1.dist-info/METADATA
phoenix_py-1.0.4.dev1.dist-info/RECORD
phoenix_py-1.0.4.dev1.dist-info/WHEEL
phoenix_py-1.0.4.dev1.dist-info/metadata.json
phoenix_py-1.0.4.dev1.dist-info/top_level.txt
